MANIFEST.in
setup.py
rocketlog/__init__.py
rocketlog/constants.py
rocketlog.egg-info/PKG-INFO
rocketlog.egg-info/SOURCES.txt
rocketlog.egg-info/dependency_links.txt
rocketlog.egg-info/requires.txt
rocketlog.egg-info/top_level.txt
rocketlog/agent/__init__.py
rocketlog/agent/agent.py
rocketlog/agent/log.py
rocketlog/agent/utils.py
rocketlog/agent/backends/__init__.py
rocketlog/agent/backends/rocket.py
rocketlog/api/__init__.py
rocketlog/api/client.py
rocketlog/api/log_handler.py
rocketlog/bin/run_flylog_agent.py