Metadata-Version: 1.0
Name: rocketlog
Version: 0.1.6
Summary: add bin file
Home-page: https://github.com/graylzhang/rocketlog
Author: grayzhang
Author-email: plyj0123@163.com
License: MIT
Platform: UNKNOWN
